odoo/addons/sale_stock_restocking_fee_invoicing/README.rst
odoo/addons/sale_stock_restocking_fee_invoicing/__init__.py
odoo/addons/sale_stock_restocking_fee_invoicing/__manifest__.py
odoo/addons/sale_stock_restocking_fee_invoicing/hooks.py
odoo/addons/sale_stock_restocking_fee_invoicing/data/product_product.xml
odoo/addons/sale_stock_restocking_fee_invoicing/i18n/fr.po
odoo/addons/sale_stock_restocking_fee_invoicing/i18n/it.po
odoo/addons/sale_stock_restocking_fee_invoicing/i18n/sale_stock_restocking_fee_invoicing.pot
odoo/addons/sale_stock_restocking_fee_invoicing/models/__init__.py
odoo/addons/sale_stock_restocking_fee_invoicing/models/res_company.py
odoo/addons/sale_stock_restocking_fee_invoicing/models/res_config_settings.py
odoo/addons/sale_stock_restocking_fee_invoicing/models/res_partner.py
odoo/addons/sale_stock_restocking_fee_invoicing/models/sale_order.py
odoo/addons/sale_stock_restocking_fee_invoicing/models/sale_order_line.py
odoo/addons/sale_stock_restocking_fee_invoicing/models/stock_move.py
odoo/addons/sale_stock_restocking_fee_invoicing/readme/CONFIGURE.md
odoo/addons/sale_stock_restocking_fee_invoicing/readme/CONTRIBUTORS.md
odoo/addons/sale_stock_restocking_fee_invoicing/readme/DESCRIPTION.md
odoo/addons/sale_stock_restocking_fee_invoicing/readme/ROADMAP.md
odoo/addons/sale_stock_restocking_fee_invoicing/readme/USAGE.md
odoo/addons/sale_stock_restocking_fee_invoicing/static/description/icon.png
odoo/addons/sale_stock_restocking_fee_invoicing/static/description/index.html
odoo/addons/sale_stock_restocking_fee_invoicing/tests/__init__.py
odoo/addons/sale_stock_restocking_fee_invoicing/tests/test_stock_return_picking.py
odoo/addons/sale_stock_restocking_fee_invoicing/views/res_company_views.xml
odoo/addons/sale_stock_restocking_fee_invoicing/views/res_config_settings_views.xml
odoo/addons/sale_stock_restocking_fee_invoicing/views/res_partner_views.xml
odoo/addons/sale_stock_restocking_fee_invoicing/views/stock_move_views.xml
odoo_addon_sale_stock_restocking_fee_invoicing-17.0.1.0.0.2.dist-info/METADATA
odoo_addon_sale_stock_restocking_fee_invoicing-17.0.1.0.0.2.dist-info/WHEEL
odoo_addon_sale_stock_restocking_fee_invoicing-17.0.1.0.0.2.dist-info/top_level.txt
odoo_addon_sale_stock_restocking_fee_invoicing-17.0.1.0.0.2.dist-info/RECORD
