Metadata-Version: 2.1
Name: odoo-addon-sale_stock_restocking_fee_invoicing
Version: 17.0.1.0.0.2
Requires-Python: >=3.10
Requires-Dist: odoo-addon-stock_picking_kind>=17.0dev,<17.1dev
Requires-Dist: odoo>=17.0a,<17.1dev
Summary: On demand charge restocking fee for accepting returned goods .
Home-page: https://github.com/OCA/stock-logistics-workflow
License: AGPL-3
Author: ACSONE SA/NV,Odoo Community Association (OCA)
Author-email: support@odoo-community.org
Classifier: Programming Language :: Python
Classifier: Framework :: Odoo
Classifier: Framework :: Odoo :: 17.0
Classifier: License :: OSI Approved :: GNU Affero General Public License v3
